nonebot_plugin_aiochatllm-0.1.7.dist-info/METADATA
nonebot_plugin_aiochatllm-0.1.7.dist-info/WHEEL
nonebot_plugin_aiochatllm-0.1.7.dist-info/entry_points.txt
nonebot_plugin_aiochatllm-0.1.7.dist-info/licenses/LICENSE
nonebot_plugin_aiochatllm/__init__.py
nonebot_plugin_aiochatllm/chat_mgr.py
nonebot_plugin_aiochatllm/config.py
nonebot_plugin_aiochatllm/mem_mgr.py
nonebot_plugin_aiochatllm/tools/__init__.py
nonebot_plugin_aiochatllm/tools/censor.py
nonebot_plugin_aiochatllm/vector_db/__init__.py
nonebot_plugin_aiochatllm/vector_db/base.py
nonebot_plugin_aiochatllm/vector_db/chromadb.py
nonebot_plugin_aiochatllm-0.1.7.dist-info/RECORD
