Metadata-Version: 2.1
Name: nonebot-plugin-aiochatllm
Version: 0.1.7
Summary: All-in-One Large Model Chat Plugin
Author-Email: Raven95676 <raven95676@gmail.com>
License: MIT
Requires-Python: >=3.10
Requires-Dist: nonebot2>=2.4.1
Requires-Dist: nonebot-plugin-alconna>=0.55.1
Requires-Dist: nonebot-plugin-localstore>=0.7.4
Requires-Dist: nonebot-plugin-uninfo>=0.6.10
Requires-Dist: nonebot-plugin-apscheduler>=0.5.0
Requires-Dist: httpx[http2]>=0.28.1
Requires-Dist: chromadb>=0.6.3
Requires-Dist: numpy>=2.2.3
